kaxi/__init__.py
kaxi/log.py
kaxi/main.py
kaxi/runner.py
kaxi-0.1.1.dist-info/LICENSE
kaxi-0.1.1.dist-info/METADATA
kaxi-0.1.1.dist-info/WHEEL
kaxi-0.1.1.dist-info/entry_points.txt
kaxi-0.1.1.dist-info/RECORD
